AUTHORS.rst
LICENSE.rst
README.rst
ez_setup.py
setup.py
chash/__init__.py
chash/ccache.py
chash/chash.py
chash.egg-info/PKG-INFO
chash.egg-info/SOURCES.txt
chash.egg-info/dependency_links.txt
chash.egg-info/requires.txt
chash.egg-info/top_level.txt
tests/test_chash.py