Metadata-Version: 1.1
Name: chash
Version: 0.1.0
Summary: Content-based hash
Home-page: https://github.com/lebedov/chash
Author: Lev Givon
Author-email: lev@columbia.edu
License: BSD
Platform: UNKNOWN
Classifier: Development Status :: 3 - Alpha
Classifier: Intended Audience :: Developers
Classifier: Intended Audience :: Science/Research
Classifier: License :: OSI Approved :: BSD License
Classifier: Operating System :: OS Independent
Classifier: Programming Language :: Python
Classifier: Topic :: Scientific/Engineering
Classifier: Topic :: Software Development
